deckhouse_sdk/__init__.py
deckhouse_sdk/conversions.py
deckhouse_sdk/hook.py
deckhouse_sdk/kubernetes.py
deckhouse_sdk/metrics.py
deckhouse_sdk/module.py
deckhouse_sdk/storage.py
deckhouse_sdk/validations.py
deckhouse_sdk/values.py
deckhouse_sdk-0.4.3.dist-info/LICENSE
deckhouse_sdk-0.4.3.dist-info/WHEEL
deckhouse_sdk-0.4.3.dist-info/METADATA
deckhouse_sdk-0.4.3.dist-info/RECORD
